flirror/__init__.py
flirror/crawler/__init__.py
flirror/crawler/google_auth.py
flirror/crawler/main.py
flirror/crawler/scheduling.py
flirror/database.py
flirror/exceptions.py
flirror/helpers.py
flirror/modules/__init__.py
flirror/modules/calendar/__init__.py
flirror/modules/calendar/templates/calendar/index.html
flirror/modules/clock/__init__.py
flirror/modules/clock/templates/clock/index.html
flirror/modules/newsfeed/__init__.py
flirror/modules/newsfeed/templates/newsfeed/index.html
flirror/modules/stocks/__init__.py
flirror/modules/stocks/templates/stocks/index.html
flirror/modules/weather/__init__.py
flirror/modules/weather/templates/weather/index.html
flirror/static/all.css
flirror/static/css/style.css
flirror/static/css/weather-icons-2.0.10.min.css
flirror/static/font/weathericons-regular-webfont.eot
flirror/static/font/weathericons-regular-webfont.svg
flirror/static/font/weathericons-regular-webfont.ttf
flirror/static/font/weathericons-regular-webfont.woff
flirror/static/font/weathericons-regular-webfont.woff2
flirror/static/scss/all.scss
flirror/templates/ajax.html
flirror/templates/error.html
flirror/templates/index.html
flirror/templates/layout.html
flirror/templates/module.html
flirror/utils.py
flirror/views.py
flirror-1.1.0.dist-info/entry_points.txt
flirror-1.1.0.dist-info/LICENSE
flirror-1.1.0.dist-info/WHEEL
flirror-1.1.0.dist-info/METADATA
flirror-1.1.0.dist-info/RECORD
