Metadata-Version: 2.1
Name: flirror
Version: 1.1.0
Summary: A smartmirror based on Flask
Home-page: https://github.com/felixedel/flirror
License: MIT
Keywords: smartmirror,magicmirror,flask
Author: Felix Edel
Author-email: felixfelix.schmidt@googlemail.com
Requires-Python: >=3.6,<4.0
Classifier: License :: OSI Approved :: MIT License
Classifier: Programming Language :: Python :: 3
Classifier: Programming Language :: Python :: 3.6
Classifier: Programming Language :: Python :: 3.7
Classifier: Programming Language :: Python :: 3.8
Requires-Dist: Flask-Assets (>=2.0,<3.0)
Requires-Dist: Pillow (>=7.0.0,<8.0.0)
Requires-Dist: alpha_vantage (>=2.1.3,<3.0.0)
Requires-Dist: arrow (>=0.15.5,<0.16.0)
Requires-Dist: click (>=7.0,<8.0)
Requires-Dist: feedparser (>=5.2.1,<6.0.0)
Requires-Dist: flask (>=1.1.1,<2.0.0)
Requires-Dist: google-api-python-client (>=1.7.11,<2.0.0)
Requires-Dist: google-auth-httplib2 (>=0.0.3,<0.0.4)
Requires-Dist: google-auth-oauthlib (>=0.4.1,<0.5.0)
Requires-Dist: gunicorn (>=20.0.4,<21.0.0)
Requires-Dist: pony (>=0.7.11,<0.8.0)
Requires-Dist: pyScss (>=1.3.5,<2.0.0)
Requires-Dist: pyowm (>=2.10.0,<3.0.0)
Requires-Dist: qrcode (>=6.1,<7.0)
Requires-Dist: schedule (>=0.6.0,<0.7.0)
Project-URL: Documentation, https://github.com/felixedel/flirror/blob/master/README.md
Project-URL: Repository, https://github.com/felixedel/flirror
